sprocket_boxcars_py/__init__.py
sprocket_boxcars_py/sprocket_boxcars_py.cpython-310-aarch64-linux-gnu.so
sprocket_boxcars_py-0.3.26.dist-info/METADATA
sprocket_boxcars_py-0.3.26.dist-info/WHEEL
sprocket_boxcars_py-0.3.26.dist-info/licenses/LICENSE
sprocket_boxcars_py-0.3.26.dist-info/RECORD
