Metadata-Version: 2.4
Name: sprocket-boxcars-py
Version: 0.3.26
Classifier: Programming Language :: Rust
Classifier: Programming Language :: Python :: Implementation :: CPython
Classifier: Programming Language :: Python :: Implementation :: PyPy
Classifier: License :: OSI Approved :: MIT License
Classifier: Development Status :: 4 - Beta
License-File: LICENSE
Summary: Python bindings for the Boxcars Rocket League replay parser
Requires-Python: >=3.7
